[
  {
    "id": 1,
    "title": "Producto A",
    "description": "Descripción del Producto A",
    "price": 15.99,
    "thumbnail": "ruta/imagen/a.jpg",
    "code": "PROD1",
    "stock": 50
  },
  {
    "id": 2,
    "title": "Producto B",
    "description": "Descripción del Producto B",
    "price": 20,
    "thumbnail": "ruta/imagen/a.jpg",
    "code": "PROD2",
    "stock": 50
  },
  {
    "id": 3,
    "title": "Producto C",
    "description": "Descripción del Producto B",
    "price": 20,
    "thumbnail": "ruta/imagen/a.jpg",
    "code": "PROD2",
    "stock": 50
  },
  {
    "id": 4,
    "title": "Producto D",
    "description": "Descripción del Producto B",
    "price": 20,
    "thumbnail": "ruta/imagen/a.jpg",
    "code": "PROD2",
    "stock": 50
  },
  {
    "id": 5,
    "title": "Producto E",
    "description": "Descripción del Producto B",
    "price": 20,
    "thumbnail": "ruta/imagen/a.jpg",
    "code": "PROD2",
    "stock": 50
  },
  {
    "id": 6,
    "title": "Producto F",
    "description": "Descripción del Producto B",
    "price": 20,
    "thumbnail": "ruta/imagen/a.jpg",
    "code": "PROD2",
    "stock": 50
  }
]